[
  {
    "l": "28974a",
    "io": "28974",
    "b": "28974",
    "r": "28974"
  },
  {
    "l": "4070",
    "io": "4070",
    "b": "4070",
    "r": "4070a"
  },
  {
    "l": "61678",
    "io": "61678",
    "b": "61678",
    "r": "11153"
  },
  {
    "l": "63965a",
    "io": "63965",
    "b": "63965",
    "r": "63965"
  },
  {
    "l": "48729b",
    "io": "48729b",
    "b": "48729b",
    "r": "48729b"
  },
  {
    "l": "3069bp04",
    "io": "3069bpb797",
    "b": "3069pb0797",
    "r": "3069bpr0286"
  },
  {
    "l": "3070bp0m",
    "io": "3070bpb140",
    "b": "3070pb140",
    "r": "3070bpr0213"
  },
  {
    "l": "88072",
    "io": "4623",
    "b": "4623b",
    "r": "88072"
  },
  {
    "l": "61678",
    "io": "11153",
    "b": "61678",
    "r": "11153"
  },
  {
    "l": "2654a",
    "io": "2654",
    "b": "2654",
    "r": "2654"
  },
  {
    "l": "5093",
    "io": "bl_5093",
    "b": "5093",
    "r": "5093"
  },
  {
    "l": "10190",
    "io": "2599",
    "b": "2599a",
    "r": "10190"
  },
  {
    "l": "3665b",
    "io": "3665",
    "b": "3665",
    "r": "3665"
  },
  {
    "l": "15068p06",
    "io": "15068pb164",
    "b": "15068pb164",
    "r": "15068pr0033"
  },
  {
    "l": "93273pz2",
    "io": "93273pb087",
    "b": "93273pb087",
    "r": "93273pr9994"
  },
  {
    "l": "3070bpe3",
    "io": "3070bpb095",
    "b": "3070pb095",
    "r": "3070bpr0157"
  },{
    "l": "3660b",
    "io": "3660",
    "b": "3660",
    "r": "3660"
  },
  {
    "l": "3003",
    "io": "3003",
    "b": "3003",
    "r": "3003"
  },
  {
    "l": "3008",
    "io": "3008",
    "b": "3008",
    "r": "3008"
  },
  {
    "l": "3001",
    "io": "3001",
    "b": "3001",
    "r": "3001"
  },
  {
    "l": "3002",
    "io": "3002",
    "b": "3002",
    "r": "3002"
  },
  {
    "l": "44301b",
    "io": "44301b",
    "b": "44301b",
    "r": "44301b"
  },
  {
    "l": "3005ptg",
    "io": "3005ptg",
    "b": "3005ptG",
    "r": "3005pr9948"
  },
  {
    "l": "15068p06",
    "io": "15068pb164",
    "b": "15068pb164",
    "r": "15068pr0033"
  },
  {
    "l": "93273pz2",
    "io": "93273pb087",
    "b": "93273pb087",
    "r": "93273pr9994"
  },
  {
    "l": "2453b",
    "io": "2453b",
    "b": "2453b",
    "r": "2453b"
  },
  {
    "l": "3069bpcc",
    "io": "3069bpb856",
    "b": "3069pb0856",
    "r": "3069bpr0300"
  },
  {
    "l": "62519",
    "io": "62519",
    "b": "62519",
    "r": "62519"
  },
  {
    "l": "62520",
    "io": "62520",
    "b": "62520",
    "r": "62520"
  },
  {
    "l": "5095",
    "io": "bl_5095",
    "b": "5095",
    "r": "5095"
  },
  {
    "l": "54657",
    "io": "44302",
    "b": "44302",
    "r": "54657"
  },
  {
    "l": "49308",
    "io": "49803",
    "b": "49308",
    "r": "49308"
  },
  {
    "l": "96910",
    "io": "99563",
    "b": "99563",
    "r": "99563"
  },
  {
    "l": "3069bp0w",
    "io": "3069bp0w",
    "b": "3069pb1275",
    "r": "3069bpr0452"
  },
  {
    "l": "64567a",
    "io": "64567b",
    "b": "64567",
    "r": "64567"
  },
  {
    "l": "71175",
    "io": "71175",
    "b": "75c12",
    "r": "75c12"
  },
  {
    "l": "5414",
    "io": "bl_5414",
    "b": "5414",
    "r": "5414"
  },
  {
    "l": "5415",
    "io": "bl_5415",
    "b": "5415",
    "r": "5415"
  },
  {
    "l": "2339",
    "io": "2339",
    "b": "2339",
    "r": "2339"
  },
  {
    "l": "61409b",
    "io": "61409",
    "b": "61409",
    "r": "61409"
  },
  {
    "l": "60481a",
    "io": "60481",
    "b": "60481",
    "r": "60481"
  },
  {
    "l": "6190a",
    "io": "6190",
    "b": "6190",
    "r": "6190"
  },
  {
    "l": "61409",
    "io": "61409b",
    "b": "61409",
    "r": "61409"
  },
  {
    "l": "75c39",
    "io": "75c39",
    "b": "75c39",
    "r": "75c39"
  },{
    "l": "75c25",
    "io": "75c25",
    "b": "75c25",
    "r": "75c25"
  },{
  "l": "3709b",
  "io": "3709b",
  "b": "3709",
  "r": "3709"
},
{
	"io": "bl_7052",
	"r": "7052",
	"b": "7052",
	"l": "7052"
},
{
	"io": "3069bpb893",
	"r": "3069bpr0321",
	"b": "3069pb0893",
	"l": "3069bpx8"
},
{
	"io": "bl_7826",
	"r": "7826",
	"b": "7826",
	"l": "7826"
}
]
