[
  {
    "l": "28974a",
    "io": "28974",
    "b": "28974",
    "r": "28974"
  },
  {
    "l": "4070",
    "io": "4070",
    "b": "4070",
    "r": "4070a"
  },
  {
    "l": "61678",
    "io": "61678",
    "b": "61678",
    "r": "11153"
  },
  {
    "l": "63965a",
    "io": "63965",
    "b": "63965",
    "r": "63965"
  },
  {
    "l": "48729b",
    "io": "48729b",
    "b": "48729b",
    "r": "48729b"
  },
  {
    "l": "3069bp04",
    "io": "3069bpb797",
    "b": "3069pb0797",
    "r": "3069bpr0286"
  },
  {
    "l": "3070bp0m",
    "io": "3070bpb140",
    "b": "3070pb140",
    "r": "3070bpr0213"
  },
  {
    "l": "2654a",
    "io": "2654",
    "b": "2654",
    "r": "2654"
  },
  {
    "l": "5093",
    "io": "bl_5093",
    "b": "5093",
    "r": "5093"
  },
  {
    "l": "10190",
    "io": "2599",
    "b": "2599a",
    "r": "10190"
  },
  {
    "l": "3665b",
    "io": "3665",
    "b": "3665",
    "r": "3665"
  },
  {
    "l": "15068p06",
    "io": "15068pb164",
    "b": "15068pb164",
    "r": "15068pr0033"
  },
  {
    "l": "93273pz2",
    "io": "93273pb087",
    "b": "93273pb087",
    "r": "93273pr9994"
  },
  {
    "l": "3070bpe3",
    "io": "3070bpb095",
    "b": "3070pb095",
    "r": "3070bpr0157"
  },
  {
    "l": "3003",
    "io": "3003",
    "b": "3003",
    "r": "3003"
  },
  {
    "l": "3008",
    "io": "3008",
    "b": "3008",
    "r": "3008"
  },
  {
    "l": "3001",
    "io": "3001",
    "b": "3001",
    "r": "3001"
  },
  {
    "l": "3002",
    "io": "3002",
    "b": "3002",
    "r": "3002"
  },
  {
    "l": "44301b",
    "io": "44301b",
    "b": "44301b",
    "r": "44301b"
  }
]